quick_start_py/__init__.py
quick_start_py/__main__.py
quick_start_py/env.py
quick_start_py/main.py
quick_start_py/say_hello.py
kgesh_sam_hello_1_py_pkg-0.0.2.dist-info/METADATA
kgesh_sam_hello_1_py_pkg-0.0.2.dist-info/WHEEL
kgesh_sam_hello_1_py_pkg-0.0.2.dist-info/entry_points.txt
kgesh_sam_hello_1_py_pkg-0.0.2.dist-info/top_level.txt
kgesh_sam_hello_1_py_pkg-0.0.2.dist-info/RECORD
