Metadata-Version: 2.4
Name: kgesh-sam-hello-1-py-pkg
Version: 0.0.2
Summary: Say hello to user - Python MCP stdio server
Author-email: Deploxy <hello@deploxy.com>
License: MIT
Keywords: deploxy,mcp,stdio-mcp-server,stdio-mcp-proxy,stdio-mcp-to-serverless
Requires-Python: >=3.8
Requires-Dist: fastmcp>=0.9.0
Provides-Extra: dev
Requires-Dist: black; extra == "dev"
Requires-Dist: mypy; extra == "dev"
Requires-Dist: pytest; extra == "dev"
